xj_task/__init__.py
xj_task/admin.py
xj_task/apps.py
xj_task/models.py
xj_task/urls.py
xj_task/validate.py
xj_task/views.py
xj_task/services/__init__.py
xj_task/services/service.py
xj_task-1.0.6.dist-info/METADATA
xj_task-1.0.6.dist-info/WHEEL
xj_task-1.0.6.dist-info/top_level.txt
xj_task-1.0.6.dist-info/RECORD
