Metadata-Version: 2.1
Name: xj-task
Version: 1.0.6
Summary: 任务模块-测试发布版
Home-page: UNKNOWN
Author: 赵向明
Author-email: sieyoo@163.com
Maintainer: 孙楷炎
Maintainer-email: sky4834@163.com
License: apache 3.0
Platform: UNKNOWN
